{
    "installed": {
        "client_id": "936836500653-i17dq29j8pmpjhries3hhbjnccbatn2q.apps.googleusercontent.com",
        "project_id": "web-shop-project-1535311053474",
        "auth_uri": "https://accounts.google.com/o/oauth2/auth",
        "token_uri": "https://www.googleapis.com/oauth2/v3/token",
        "auth_provider_x509_cert_url": "https://www.googleapis.com/oauth2/v1/certs",
        "client_secret": "4uITUj-yviaJqypJg1CW_Lad",
        "redirect_uris": [
            "urn:ietf:wg:oauth:2.0:oob",
            "http://localhost"
        ]
    }
}